llama_deploy/__init__.py
llama_deploy/apiserver/__init__.py
llama_deploy/apiserver/__main__.py
llama_deploy/apiserver/app.py
llama_deploy/apiserver/deployment.py
llama_deploy/apiserver/deployment_config_parser.py
llama_deploy/apiserver/server.py
llama_deploy/apiserver/settings.py
llama_deploy/apiserver/stats.py
llama_deploy/apiserver/tracing.py
llama_deploy/apiserver/routers/__init__.py
llama_deploy/apiserver/routers/deployments.py
llama_deploy/apiserver/routers/status.py
llama_deploy/apiserver/source_managers/__init__.py
llama_deploy/apiserver/source_managers/base.py
llama_deploy/apiserver/source_managers/git.py
llama_deploy/apiserver/source_managers/local.py
llama_deploy/cli/__init__.py
llama_deploy/cli/__main__.py
llama_deploy/cli/config.py
llama_deploy/cli/deploy.py
llama_deploy/cli/init.py
llama_deploy/cli/run.py
llama_deploy/cli/serve.py
llama_deploy/cli/sessions.py
llama_deploy/cli/status.py
llama_deploy/cli/internal/config.py
llama_deploy/cli/internal/utils.py
llama_deploy/client/__init__.py
llama_deploy/client/base.py
llama_deploy/client/client.py
llama_deploy/client/models/__init__.py
llama_deploy/client/models/apiserver.py
llama_deploy/client/models/model.py
llama_deploy/types/__init__.py
llama_deploy/types/apiserver.py
llama_deploy/types/core.py
llama_deploy-0.9.1.dist-info/METADATA
llama_deploy-0.9.1.dist-info/WHEEL
llama_deploy-0.9.1.dist-info/entry_points.txt
llama_deploy-0.9.1.dist-info/licenses/LICENSE
llama_deploy-0.9.1.dist-info/RECORD
