Metadata-Version: 2.4
Name: llama-deploy
Version: 0.9.1
Author-email: Logan Markewich <logan.markewich@live.com>, Andrei Fajardo <andrei@runllama.ai>
Maintainer-email: Logan Markewich <logan@llamaindex.ai>, Andrei Fajardo <andrei@runllama.ai>, Jerry Liu <jerry@llamaindex.ai>
License-File: LICENSE
Requires-Python: <4.0,>=3.10
Requires-Dist: asgiref<4,>=3.8.1
Requires-Dist: brotli>=1.1.0
Requires-Dist: fastapi>=0.109.1
Requires-Dist: fastmcp>=2.8.1
Requires-Dist: gitpython<4,>=3.1.43
Requires-Dist: llama-index-core<0.13.0,>=0.11.17
Requires-Dist: llama-index-workflows>=0.2.1
Requires-Dist: platformdirs<5,>=4.3.6
Requires-Dist: prometheus-client<0.22,>=0.21.1
Requires-Dist: pydantic!=2.10
Requires-Dist: pydantic-settings<3.0,>=2.0
Requires-Dist: python-dotenv<2,>=1.0.1
Requires-Dist: python-multipart<0.0.19,>=0.0.18
Requires-Dist: pyyaml>6
Requires-Dist: rich<14,>=13.9.4
Requires-Dist: typing-extensions<5,>=4.0.0
Requires-Dist: uvicorn[standard]>=0.12.0
Requires-Dist: websockets>=15.0.1
Provides-Extra: kafka
Requires-Dist: aiokafka<0.12,>=0.11.0; extra == 'kafka'
Requires-Dist: kafka-python-ng<3,>=2.2.2; extra == 'kafka'
Provides-Extra: observability
Requires-Dist: opentelemetry-api<2.0,>=1.20.0; extra == 'observability'
Requires-Dist: opentelemetry-exporter-jaeger<2.0,>=1.20.0; extra == 'observability'
Requires-Dist: opentelemetry-exporter-otlp<2.0,>=1.20.0; extra == 'observability'
Requires-Dist: opentelemetry-instrumentation-asyncio<1.0,>=0.41b0; extra == 'observability'
Requires-Dist: opentelemetry-sdk<2.0,>=1.20.0; extra == 'observability'
Provides-Extra: rabbitmq
Requires-Dist: aio-pika<10,>=9.4.2; extra == 'rabbitmq'
Provides-Extra: redis
Requires-Dist: redis<6,>=5.0.7; extra == 'redis'
